{
  "title": "Aerospace Engineering Visiting Scholars Fund",
  "description": "To provide support for visiting speakers in the Department of Aerospace Engineering. This includes stipends, travel, accommodations and any other associated expenses.",
  "marketingContent": "To provide support for visiting speakers in the Department of Aerospace Engineering at CU Boulder.  This includes stipends, travel, accommodations and any other associated expenses.",
  "campus": "904",
  "allocationCode": "0123294",
  "interest": "907"
}