{
  "title": "Charles A. Barth Scholarship Endowment Fund in Space Research",
  "description": "To provide scholarship support for a senior student at CU Boulder in studies related to space research projects at LASP at the University of Colorado Boulder.",
  "marketingContent": "<p>To provide scholarship support for a senior student at CU&nbsp;Boulder in studies related to space research projects at LASP at the University of Colorado Boulder.</p>\r\n",
  "campus": "904",
  "allocationCode": "0151076",
  "interest": "907"
}